software_project_estimator/__init__.py
software_project_estimator/event.py
software_project_estimator/observer.py
software_project_estimator/project.py
software_project_estimator/task.py
software_project_estimator/simulation/__init__.py
software_project_estimator/simulation/iteration.py
software_project_estimator/simulation/models.py
software_project_estimator/simulation/monte_carlo.py
software_project_estimator/simulation/states/__init__.py
software_project_estimator/simulation/states/iteration_base_state.py
software_project_estimator/simulation/states/iteration_state_calculating_days.py
software_project_estimator/simulation/states/iteration_state_calculating_weeks.py
software_project_estimator/simulation/states/iteration_state_error.py
software_project_estimator/simulation/states/iteration_state_finalizing.py
software_project_estimator/simulation/states/iteration_state_successful.py
software_project_estimator/simulation/states/iteration_state_uninitialized.py
python_software_project_estimator-0.1.2.dist-info/LICENSE
python_software_project_estimator-0.1.2.dist-info/METADATA
python_software_project_estimator-0.1.2.dist-info/WHEEL
python_software_project_estimator-0.1.2.dist-info/top_level.txt
python_software_project_estimator-0.1.2.dist-info/RECORD
