Metadata-Version: 2.1
Name: python-software-project-estimator
Version: 0.1.2
Summary: Estimate the time and cost of a software project
Author-email: Matthew Sewell <matthew@ragingbits.com>
Project-URL: Hompage, https://artificiallyunintelligent.com
Project-URL: Source, https://github.com/matthewsewell/software-project-estimator
Classifier: Development Status :: 3 - Alpha
Classifier: Intended Audience :: Developers
Classifier: License :: OSI Approved :: MIT License
Classifier: Programming Language :: Python :: 3
Classifier: Programming Language :: Python :: 3.9
Classifier: Programming Language :: Python :: 3.10
Requires-Python: >=3.9
License-File: LICENSE
Requires-Dist: numpy
Requires-Dist: holidays
Requires-Dist: pydantic
